Metadata-Version: 2.1
Name: text-complexity-computer
Version: 0.2
Summary: A library for evaluate text difficulty in French.
Author: le-smog
Author-email: le-smog@gmx.com
License: LGPLv3
Classifier: Development Status :: 3 - Alpha
Classifier: Intended Audience :: Developers
Classifier: Intended Audience :: Education
Classifier: Intended Audience :: Science/Research
Classifier: License :: OSI Approved :: GNU Lesser General Public License v3 (LGPLv3)
Classifier: Programming Language :: Python :: 3
Classifier: Programming Language :: Python :: 3.8
Classifier: Programming Language :: Python :: 3.8
Classifier: Programming Language :: Python :: 3.9
Classifier: Programming Language :: Python :: 3.10
Classifier: Programming Language :: Python :: 3.11
Classifier: Topic :: Software Development :: Libraries
Classifier: Topic :: Software Development :: Libraries :: Python Modules
Requires-Python: >=3.8
License-File: LICENSE.txt
Requires-Dist: spacy
Requires-Dist: numpy
Requires-Dist: pandas
Requires-Dist: pyahocorasick
Requires-Dist: scikit-learn
